dbdatareader.py
dbdatareader-0.1a10.dist-info/LICENSE
dbdatareader-0.1a10.dist-info/METADATA
dbdatareader-0.1a10.dist-info/WHEEL
dbdatareader-0.1a10.dist-info/top_level.txt
dbdatareader-0.1a10.dist-info/RECORD
