Metadata-Version: 2.1
Name: dbdatareader
Version: 0.1a10
Summary: dbDataReader - Data Reader for .NET IDataReader
Home-page: https://github.com/DataBooster/PyWebApi
Author: Abel Cheng
Author-email: abelcys@gmail.com
License: MIT
Keywords: IDataReader,DataReader,DataBooster,WebAPI,forward-only,IResultSet,ListOfList,ListOfDict,DictOfList
Platform: any
Requires-Python: >=3
